{"openapi":"3.0.1","info":{"title":"TaskBoard","version":"0.0.1"},"servers":[{"url":"http://localhost:8080","description":"Generated server url"}],"paths":{"/api/tasks/{id}":{"get":{"tags":["Tasks"],"summary":"Get task by ID.","operationId":"getById_1","parameters":[{"name":"id","in":"path","required":true,"schema":{"type":"string","format":"uuid"}}],"responses":{"200":{"description":"The task with the provided ID as a JSON object.","content":{"application/json":{"schema":{"$ref":"#/components/schemas/TaskDto"}}}},"400":{"description":"No task with the provided ID could not be found.","content":{"*/*":{"schema":{"$ref":"#/components/schemas/TaskDto"}}}}}},"put":{"tags":["Tasks"],"summary":"Updates an existing task.","operationId":"update","parameters":[{"name":"id","in":"path","required":true,"schema":{"type":"string","format":"uuid"}}],"requestBody":{"content":{"application/json":{"schema":{"$ref":"#/components/schemas/TaskDto"}}},"required":true},"responses":{"200":{"description":"The updated task as a JSON object.","content":{"application/json":{"schema":{"$ref":"#/components/schemas/TaskDto"}}}},"400":{"description":"IDs do not match or no task or user with the provided IDs could be found.","content":{"*/*":{"schema":{"$ref":"#/components/schemas/TaskDto"}}}}}},"delete":{"tags":["Tasks"],"summary":"Delete a task.","operationId":"delete","parameters":[{"name":"id","in":"path","required":true,"schema":{"type":"string","format":"uuid"}}],"responses":{"200":{"description":"The task with the provided ID was successfully deleted."},"400":{"description":"No task with the provided ID could be found."}}}},"/api/users":{"get":{"tags":["Users"],"summary":"Get all users.","operationId":"getAll","responses":{"200":{"description":"All users as a JSON array.","content":{"application/json":{"schema":{"$ref":"#/components/schemas/UserDto"}}}}}},"post":{"tags":["Users"],"summary":"Creates a new user.","operationId":"create","requestBody":{"content":{"application/json":{"schema":{"$ref":"#/components/schemas/UserDto"}}},"required":true},"responses":{"200":{"description":"The new user as a JSON object.","content":{"application/json":{"schema":{"$ref":"#/components/schemas/UserDto"}}}},"400":{"description":"An ID was provided or a user with the same name already exists.","content":{"application/json":{}}}}}},"/api/tasks":{"get":{"tags":["Tasks"],"summary":"Get all tasks.","operationId":"getAll_1","responses":{"200":{"description":"All tasks as a JSON array.","content":{"application/json":{"schema":{"$ref":"#/components/schemas/TaskDto"}}}}}},"post":{"tags":["Tasks"],"summary":"Creates a new task.","operationId":"create_1","requestBody":{"content":{"application/json":{"schema":{"$ref":"#/components/schemas/TaskDto"}}},"required":true},"responses":{"200":{"description":"The new task as a JSON object.","content":{"application/json":{"schema":{"$ref":"#/components/schemas/TaskDto"}}}},"400":{"description":"ID present or user with the provided user ID could not be found.","content":{"*/*":{"schema":{"$ref":"#/components/schemas/TaskDto"}}}}}}},"/api/users/{id}":{"get":{"tags":["Users"],"summary":"Get a user by ID.","operationId":"getById","parameters":[{"name":"id","in":"path","required":true,"schema":{"type":"string","format":"uuid"}}],"responses":{"200":{"description":"The user as a JSON object.","content":{"application/json":{"schema":{"$ref":"#/components/schemas/UserDto"}}}},"404":{"description":"No user with the provided ID was found.","content":{"application/json":{}}}}}},"/api/tasks/status/{status}":{"get":{"tags":["Tasks"],"summary":"Get tasks by status.","operationId":"getByStatus","parameters":[{"name":"status","in":"path","required":true,"schema":{"type":"string","enum":["TODO","DOING","DONE"]}}],"responses":{"200":{"description":"The tasks with the provided status as a JSON array.","content":{"application/json":{"schema":{"$ref":"#/components/schemas/TaskDto"}}}},"400":{"description":"No task with the provided ID could not be found.","content":{"*/*":{"schema":{"type":"array","items":{"$ref":"#/components/schemas/TaskDto"}}}}}}}},"/api/tasks/assignee/{userId}":{"get":{"tags":["Tasks"],"summary":"Get tasks by assignee.","operationId":"getByStatus_1","parameters":[{"name":"userId","in":"path","required":true,"schema":{"type":"string","format":"uuid"}}],"responses":{"200":{"description":"The tasks with the provided status as a JSON array.","content":{"application/json":{"schema":{"$ref":"#/components/schemas/TaskDto"}}}},"400":{"description":"No task with the provided ID could not be found.","content":{"*/*":{"schema":{"type":"array","items":{"$ref":"#/components/schemas/TaskDto"}}}}}}}}},"components":{"schemas":{"TaskDto":{"required":["description","title"],"type":"object","properties":{"id":{"type":"string","format":"uuid"},"createdAt":{"type":"string","format":"date-time"},"updatedAt":{"type":"string","format":"date-time"},"title":{"maxLength":255,"minLength":0,"type":"string"},"description":{"type":"string"},"status":{"type":"string","enum":["TODO","DOING","DONE"]},"assignee":{"$ref":"#/components/schemas/UserDto"}}},"UserDto":{"required":["name"],"type":"object","properties":{"id":{"type":"string","format":"uuid"},"createdAt":{"type":"string","format":"date-time"},"name":{"pattern":"\\w+","type":"string"}}}}}}